cdc_automation/__init__.py
cdc_automation/api_request/__init__.py
cdc_automation/api_request/base.py
cdc_automation/api_request/package_info.py
cdc_automation/tools/AES_RSA_Crypto.py
cdc_automation/tools/__init__.py
cdc_automation/tools/small_tool.py
cdc_automation-0.0.14.dist-info/licenses/LICENSE
cdc_automation-0.0.14.dist-info/METADATA
cdc_automation-0.0.14.dist-info/WHEEL
cdc_automation-0.0.14.dist-info/top_level.txt
cdc_automation-0.0.14.dist-info/RECORD
