Metadata-Version: 2.4
Name: cdc-automation
Version: 0.0.14
Summary: only for cdc own study used
Author: Wayne Chen
Author-email: kensmart123@yahoo.com.tw
Classifier: Programming Language :: Python :: 3
Classifier: Operating System :: OS Independent
Requires-Python: >=3.6
License-File: LICENSE
Requires-Dist: requests
Requires-Dist: python-json-logger
Requires-Dist: concurrent-log-handler
Requires-Dist: jsonschema
Requires-Dist: webcolors
Requires-Dist: rfc3339-validator
Requires-Dist: isoduration
Requires-Dist: fqdn
Requires-Dist: idna
Requires-Dist: rfc3987
Requires-Dist: jsonpointer
Requires-Dist: uri-template
Requires-Dist: pycryptodome
Dynamic: author
Dynamic: author-email
Dynamic: classifier
Dynamic: description
Dynamic: description-content-type
Dynamic: license-file
Dynamic: requires-dist
Dynamic: requires-python
Dynamic: summary
